bedrockx/__init__.py
bedrockx/file/__init__.py
bedrockx/file/utils.py
bedrockx/process/__init__.py
bedrockx/process/data_process.py
bedrockx/process/multi_thread_process.py
bedrockx/utils/__init__.py
bedrockx/utils/log_manage.py
bedrockx/utils/utils.py
bedrockx-0.1.0.dist-info/METADATA
bedrockx-0.1.0.dist-info/WHEEL
bedrockx-0.1.0.dist-info/top_level.txt
bedrockx-0.1.0.dist-info/RECORD
