Metadata-Version: 2.4
Name: bedrockx
Version: 0.1.0
Summary: Add your description here
Requires-Python: >=3.10
Requires-Dist: loguru>=0.7.3
Requires-Dist: tqdm>=4.67.1
Requires-Dist: openpyxl>=3.1.5
Requires-Dist: pandas>=2.3.3
